{
	"info": {
		"_postman_id": "c204ed36-91cf-4d0a-a22c-90d1189147d4",
		"name": "ChatApp",
		"schema": "https://schema.getpostman.com/json/collection/v2.1.0/collection.json",
		"_exporter_id": "31481705"
	},
	"item": [
		{
			"name": "Post user",
			"request": {
				"method": "POST",
				"header": [],
				"body": {
					"mode": "raw",
					"raw": "{\n    \"userName\": \"Juliana\",\n    \"password\": \"1234\",\n    \"token\": \"token2\"\n}\n",
					"options": {
						"raw": {
							"language": "json"
						}
					}
				},
				"url": {
					"raw": "http://localhost:3000/users",
					"protocol": "http",
					"host": [
						"localhost"
					],
					"port": "3000",
					"path": [
						"users"
					]
				}
			},
			"response": []
		},
		{
			"name": "Get userName",
			"request": {
				"method": "GET",
				"header": [],
				"url": {
					"raw": "http://localhost:3000/users/Mario",
					"protocol": "http",
					"host": [
						"localhost"
					],
					"port": "3000",
					"path": [
						"users",
						"Mario"
					]
				}
			},
			"response": []
		},
		{
			"name": "Post chat",
			"request": {
				"method": "POST",
				"header": [],
				"body": {
					"mode": "raw",
					"raw": "{\n    \"name\": \"Sala3\",\n    \"createdBy\": \"Chico\"\n}",
					"options": {
						"raw": {
							"language": "json"
						}
					}
				},
				"url": {
					"raw": "http://localhost:3000/chatrooms",
					"protocol": "http",
					"host": [
						"localhost"
					],
					"port": "3000",
					"path": [
						"chatrooms"
					]
				}
			},
			"response": []
		},
		{
			"name": "Get chatRooms",
			"request": {
				"method": "GET",
				"header": [],
				"url": {
					"raw": "http://localhost:3000/chatrooms",
					"protocol": "http",
					"host": [
						"localhost"
					],
					"port": "3000",
					"path": [
						"chatrooms"
					]
				}
			},
			"response": []
		},
		{
			"name": "Get chatRoomsById",
			"request": {
				"method": "GET",
				"header": [],
				"url": {
					"raw": "http://localhost:3000/chatrooms/65d38479e1736cf4239dfaca",
					"protocol": "http",
					"host": [
						"localhost"
					],
					"port": "3000",
					"path": [
						"chatrooms",
						"65d38479e1736cf4239dfaca"
					]
				}
			},
			"response": []
		},
		{
			"name": "Post message",
			"request": {
				"method": "POST",
				"header": [],
				"body": {
					"mode": "raw",
					"raw": "{\n  \"chatId\": \"65d4f00037f5e02fc536d37c\",\n  \"senderId\": \"65cddc037bbfaa75b9d8baaf\",\n  \"text\": \"Buenos dias\"\n}\n",
					"options": {
						"raw": {
							"language": "json"
						}
					}
				},
				"url": {
					"raw": "http://localhost:3000/messages",
					"protocol": "http",
					"host": [
						"localhost"
					],
					"port": "3000",
					"path": [
						"messages"
					]
				}
			},
			"response": []
		},
		{
			"name": "Get message",
			"request": {
				"method": "GET",
				"header": [],
				"url": {
					"raw": "http://localhost:3000/messages/65d4f00037f5e02fc536d37c",
					"protocol": "http",
					"host": [
						"localhost"
					],
					"port": "3000",
					"path": [
						"messages",
						"65d4f00037f5e02fc536d37c"
					]
				}
			},
			"response": []
		}
	]
}